pydelta/PyDelta.py
pydelta/__init__.py
pydelta/anti_debugger.py
pydelta/code_compressor_and_encryptor.py
pydelta/delta_random.py
pydelta/ids_refactor.py
pydelta/import2inlineimport.py
pydelta/reserved_names.py
pydelta/runtime_code.py
pydelta/string_encryption.py
pydeltaobfuscator-0.1.1.dist-info/LICENSE
pydeltaobfuscator-0.1.1.dist-info/METADATA
pydeltaobfuscator-0.1.1.dist-info/WHEEL
pydeltaobfuscator-0.1.1.dist-info/entry_points.txt
pydeltaobfuscator-0.1.1.dist-info/top_level.txt
pydeltaobfuscator-0.1.1.dist-info/RECORD
