Metadata-Version: 2.1
Name: pydeltaobfuscator
Version: 0.1.1
License-File: LICENSE
Requires-Dist: cryptography
Requires-Dist: argparse
